driver/__init__.py
driver/contextual_json_driver.py
driver/json_driver.py
driver/stop_token_json_driver.py
driver/streaming_contextual_driver.py
prefilled_json/__init__.py
prefilled_json/driver.py
prefilled_json/types.py
prefilled_json/vllm_integration.py
prefilled_json-0.2.2.dist-info/licenses/LICENSE
vllm_plugin/__init__.py
vllm_plugin/json_prefilled_plugin.py
prefilled_json-0.2.2.dist-info/METADATA
prefilled_json-0.2.2.dist-info/WHEEL
prefilled_json-0.2.2.dist-info/top_level.txt
prefilled_json-0.2.2.dist-info/RECORD
