Metadata-Version: 2.4
Name: prefilled-json
Version: 0.2.2
Summary: Generate valid JSON with small LLMs using stop token control and field-by-field completion
Author: prefilled-json contributors
License: MIT License
Project-URL: Homepage, https://github.com/devlinb/prefilled-json
Project-URL: Repository, https://github.com/devlinb/prefilled-json
Project-URL: Documentation, https://github.com/devlinb/prefilled-json#readme
Project-URL: Bug Reports, https://github.com/devlinb/prefilled-json/issues
Keywords: json,llm,ai,vllm,small-models,json-generation,stop-tokens,reliable-json
Classifier: Development Status :: 5 - Production/Stable
Classifier: Intended Audience :: Developers
Classifier: Intended Audience :: Science/Research
Classifier: License :: OSI Approved :: MIT License
Classifier: Topic :: Scientific/Engineering :: Artificial Intelligence
Classifier: Topic :: Software Development :: Libraries :: Python Modules
Classifier: Programming Language :: Python :: 3
Classifier: Programming Language :: Python :: 3.8
Classifier: Programming Language :: Python :: 3.9
Classifier: Programming Language :: Python :: 3.10
Classifier: Programming Language :: Python :: 3.11
Classifier: Programming Language :: Python :: 3.12
Requires-Python: >=3.8
License-File: LICENSE
Provides-Extra: dev
Requires-Dist: pytest>=7.0.0; extra == "dev"
Requires-Dist: pytest-cov>=4.0.0; extra == "dev"
Requires-Dist: black>=23.0.0; extra == "dev"
Requires-Dist: isort>=5.12.0; extra == "dev"
Requires-Dist: flake8>=6.0.0; extra == "dev"
Requires-Dist: mypy>=1.0.0; extra == "dev"
Provides-Extra: vllm
Requires-Dist: vllm>=0.6.0; extra == "vllm"
Provides-Extra: all
Requires-Dist: vllm>=0.6.0; extra == "all"
Dynamic: license-file
